sqlflow_models/__init__.py
sqlflow_models/_version.py
sqlflow_models/arima_with_stl_decomposition.py
sqlflow_models/auto_estimator.py
sqlflow_models/custom_model_example.py
sqlflow_models/deep_embedding_cluster.py
sqlflow_models/dnnclassifier.py
sqlflow_models/dnnclassifier_functional_api_example.py
sqlflow_models/dnnregressor.py
sqlflow_models/gcn.py
sqlflow_models/native_keras.py
sqlflow_models/one_class_svm.py
sqlflow_models/rnn_based_time_series.py
sqlflow_models/rnnclassifier.py
sqlflow_models/score_card.py
sqlflow_models/simple_dnn_generator.py
sqlflow_models-0.1.3.dist-info/LICENSE
sqlflow_models-0.1.3.dist-info/METADATA
sqlflow_models-0.1.3.dist-info/WHEEL
sqlflow_models-0.1.3.dist-info/top_level.txt
sqlflow_models-0.1.3.dist-info/RECORD
