Metadata-Version: 2.1
Name: sqlflow-models
Version: 0.1.3
Summary: Premade Models for SQLFlow.
Home-page: https://github.com/sql-machine-learning/models
Author: Yang Yang
Author-email: yzhdoudou@gmail.com
License: Apache License 2.0
Platform: UNKNOWN
Classifier: License :: OSI Approved :: Apache Software License
Classifier: Programming Language :: Python
Classifier: Programming Language :: Python :: 3
Classifier: Programming Language :: Python :: 3.6
Classifier: Programming Language :: Python :: Implementation :: CPython
Classifier: Programming Language :: Python :: Implementation :: PyPy
Requires-Python: >=3.6.0
License-File: LICENSE
Requires-Dist: tensorflow-datasets
Requires-Dist: scikit-learn
Requires-Dist: pandas (>=0.25.1)
Requires-Dist: adanet (>=0.8.0)
Requires-Dist: statsmodels
Requires-Dist: scipy
